.gitignore
.lsan.suppressions
CHANGELOG.md
LICENSE
Makefile
README.md
benchmark.py
requirements-dev.txt
setup.cfg
setup.py
.github/workflows/ci.yml
jsonslicer/__init__.pyi
jsonslicer/py.typed
jsonslicer.egg-info/PKG-INFO
jsonslicer.egg-info/SOURCES.txt
jsonslicer.egg-info/dependency_links.txt
jsonslicer.egg-info/top_level.txt
src/construct_handlers.cc
src/construct_handlers.hh
src/encoding.cc
src/encoding.hh
src/handlers.cc
src/handlers.hh
src/jsonslicer.hh
src/jsonslicer_construction.cc
src/jsonslicer_iteration.cc
src/jsonslicer_type.cc
src/output_formatting.cc
src/output_formatting.hh
src/py_module.cc
src/pymutindex.cc
src/pymutindex.hh
src/pyobjlist.cc
src/pyobjlist.hh
src/pyobjptr.hh
src/seek_handlers.cc
src/seek_handlers.hh
tests/__init__.py
tests/common.py
tests/test_basic.py
tests/test_encodings.py
tests/test_leaks.py
tests/test_path_modes.py
tests/test_paths.py
tests/test_readme.py
tests/test_types.py
tests/test_yajl.py