Metadata-Version: 2.1
Name: jsonslicer
Version: 0.1.8
Summary: Stream JSON parser with iterator interface
Home-page: https://github.com/AMDmi3/jsonslicer
Author: Dmitry Marakasov
Author-email: amdmi3@amdmi3.ru
License: MIT
Keywords: json,parser,pull,stream
Classifier: Development Status :: 4 - Beta
Classifier: Intended Audience :: Developers
Classifier: License :: OSI Approved :: MIT License
Classifier: Programming Language :: C++
Classifier: Programming Language :: Python :: 3 :: Only
Classifier: Programming Language :: Python :: 3.6
Classifier: Programming Language :: Python :: 3.7
Classifier: Programming Language :: Python :: 3.8
Classifier: Programming Language :: Python :: 3.9
Classifier: Programming Language :: Python :: 3.10
Classifier: Programming Language :: Python :: 3.11
License-File: LICENSE
